tfne/__init__.py
tfne/evolution_engine.py
tfne/helper_functions.py
tfne/algorithms/__init__.py
tfne/algorithms/base_algorithm.py
tfne/algorithms/codeepneat/__init__.py
tfne/algorithms/codeepneat/_codeepneat_config_processing.py
tfne/algorithms/codeepneat/_codeepneat_evolution_bp.py
tfne/algorithms/codeepneat/_codeepneat_evolution_mod.py
tfne/algorithms/codeepneat/_codeepneat_initialization.py
tfne/algorithms/codeepneat/_codeepneat_selection_bp.py
tfne/algorithms/codeepneat/_codeepneat_selection_mod.py
tfne/algorithms/codeepneat/_codeepneat_speciation_bp.py
tfne/algorithms/codeepneat/_codeepneat_speciation_mod.py
tfne/algorithms/codeepneat/codeepneat.py
tfne/deserialization/__init__.py
tfne/deserialization/deserialization.py
tfne/deserialization/codeepneat/__init__.py
tfne/deserialization/codeepneat/codeepneat_deserialization.py
tfne/encodings/__init__.py
tfne/encodings/base_encoding.py
tfne/encodings/base_genome.py
tfne/encodings/codeepneat/__init__.py
tfne/encodings/codeepneat/codeepneat_blueprint.py
tfne/encodings/codeepneat/codeepneat_encoding.py
tfne/encodings/codeepneat/codeepneat_genome.py
tfne/encodings/codeepneat/codeepneat_model.py
tfne/encodings/codeepneat/codeepneat_optimizer_factory.py
tfne/encodings/codeepneat/modules/__init__.py
tfne/encodings/codeepneat/modules/codeepneat_module_association.py
tfne/encodings/codeepneat/modules/codeepneat_module_base.py
tfne/encodings/codeepneat/modules/codeepneat_module_conv2dmaxpool2ddropout.py
tfne/encodings/codeepneat/modules/codeepneat_module_densedropout.py
tfne/environments/__init__.py
tfne/environments/base_environment.py
tfne/environments/cifar10_environment.py
tfne/environments/mnist_environment.py
tfne/environments/xor_environment.py
tfne/experimental/__init__.py
tfne/experimental/algorithms/__init__.py
tfne/experimental/encodings/__init__.py
tfne/experimental/environments/__init__.py
tfne/populations/__init__.py
tfne/populations/base_population.py
tfne/populations/codeepneat/__init__.py
tfne-0.21.1.dist-info/LICENSE
tfne-0.21.1.dist-info/METADATA
tfne-0.21.1.dist-info/WHEEL
tfne-0.21.1.dist-info/top_level.txt
tfne-0.21.1.dist-info/RECORD
