Metadata-Version: 2.1
Name: tfne
Version: 0.21.1
Summary: A modular Neuroevolution framework for Tensorflow models
Home-page: https://github.com/PaulPauls/Tensorflow-Neuroevolution
Author: Paul Pauls
Author-email: tfne@paulpauls.de
License: UNKNOWN
Platform: UNKNOWN
Classifier: Programming Language :: Python :: 3
Classifier: License :: OSI Approved :: Apache Software License
Classifier: Operating System :: OS Independent
Requires-Python: >= 3.7
Requires-Dist: tensorflow (>=2.0.0)
Requires-Dist: ray
Requires-Dist: graphviz
Requires-Dist: matplotlib
Requires-Dist: PyQt5
Requires-Dist: pydot
